analysis_core/__init__.py
analysis_core/__main__.py
analysis_core/config.py
analysis_core/orchestrator.py
analysis_core/core/__init__.py
analysis_core/core/orchestration.py
analysis_core/core/utils.py
analysis_core/prompts/__init__.py
analysis_core/services/__init__.py
analysis_core/services/llm.py
analysis_core/services/parse_json_list.py
analysis_core/specs/__init__.py
analysis_core/specs/hierarchical_specs.json
analysis_core/steps/__init__.py
analysis_core/steps/embedding.py
analysis_core/steps/extraction.py
analysis_core/steps/hierarchical_aggregation.py
analysis_core/steps/hierarchical_clustering.py
analysis_core/steps/hierarchical_initial_labelling.py
analysis_core/steps/hierarchical_merge_labelling.py
analysis_core/steps/hierarchical_overview.py
analysis_core/steps/hierarchical_visualization.py
kouchou_ai_analysis_core-0.1.0.dist-info/METADATA
kouchou_ai_analysis_core-0.1.0.dist-info/WHEEL
kouchou_ai_analysis_core-0.1.0.dist-info/entry_points.txt
kouchou_ai_analysis_core-0.1.0.dist-info/RECORD
